regfile.sv
module regfile (
    output logic [63:0] ReadData1,
    output logic [63:0] ReadData2,
    input logic [63:0] WriteData,
    input logic [4:0] ReadRegister1,
    input logic [4:0] ReadRegister2,
    input logic [4:0] WriteRegister,
    input logic RegWrite,
    input logic clk
);

    // 32 x 64-bit register array
    logic [63:0] registers [31:0];

    // Write operation - on posedge clk
    always_ff @(posedge clk) begin
        if (RegWrite && (WriteRegister != 31)) begin
            registers[WriteRegister] <= WriteData;
        end
        // Always keep register 31 as zero
        registers[31] <= 64'd0;
    end

    // Read operation - combinational
    assign ReadData1 = registers[ReadRegister1];
    assign ReadData2 = registers[ReadRegister2];
endmodule

regstim.sv
// Test bench for Register file
`timescale 1ns/10ps

module regstim(); 		

	parameter ClockDelay = 5000;

	logic	[4:0] 	ReadRegister1, ReadRegister2, WriteRegister;
	logic [63:0]	WriteData;
	logic 			RegWrite, clk;
	logic [63:0]	ReadData1, ReadData2;

	integer i;

	// Your register file MUST be named "regfile".
	// Also you must make sure that the port declarations
	// match up with the module instance in this stimulus file.
	regfile dut (.ReadData1, .ReadData2, .WriteData, 
					 .ReadRegister1, .ReadRegister2, .WriteRegister,
					 .RegWrite, .clk);

	// Force %t's to print in a nice format.
	initial $timeformat(-9, 2, " ns", 10);

	initial begin // Set up the clock
		clk <= 0;
		forever #(ClockDelay/2) clk <= ~clk;
	end

	initial begin
		$dumpfile("reg.vcd");
        $dumpvars(0, regstim);
		// Try to write the value 0xA0 into register 31.
		// Register 31 should always be at the value of 0.
		RegWrite <= 5'd0;
		ReadRegister1 <= 5'd0;
		ReadRegister2 <= 5'd0;
		WriteRegister <= 5'd31;
		WriteData <= 64'h00000000000000A0;
		@(posedge clk);
		
		$display("%t Attempting overwrite of register 31, which should always be 0", $time);
		RegWrite <= 1;
		@(posedge clk);

		// Write a value into each  register.
		$display("%t Writing pattern to all registers.", $time);
		for (i=0; i<31; i=i+1) begin
			RegWrite <= 0;
			ReadRegister1 <= i-1;
			ReadRegister2 <= i;
			WriteRegister <= i;
			WriteData <= i*64'h0000010204080001;
			@(posedge clk);
			
			RegWrite <= 1;
			@(posedge clk);
		end

		// Go back and verify that the registers
		// retained the data.
		$display("%t Checking pattern.", $time);
		for (i=0; i<32; i=i+1) begin
			RegWrite <= 0;
			ReadRegister1 <= i-1;
			ReadRegister2 <= i;
			WriteRegister <= i;
			WriteData <= i*64'h0000000000000100+i;
			@(posedge clk);
		end
		$stop;
	end
endmodule

reg.vcd
$date
	Thu Oct  2 21:39:48 2025
$end
$version
	Icarus Verilog
$end
$timescale
	10ps
$end
$scope module regstim $end
$var wire 64 ! ReadData2 [63:0] $end
$var wire 64 " ReadData1 [63:0] $end
$var reg 5 # ReadRegister1 [4:0] $end
$var reg 5 $ ReadRegister2 [4:0] $end
$var reg 1 % RegWrite $end
$var reg 64 & WriteData [63:0] $end
$var reg 5 ' WriteRegister [4:0] $end
$var reg 1 ( clk $end
$var integer 32 ) i [31:0] $end
$scope module dut $end
$var wire 64 * ReadData1 [63:0] $end
$var wire 64 + ReadData2 [63:0] $end
$var wire 5 , ReadRegister1 [4:0] $end
$var wire 5 - ReadRegister2 [4:0] $end
$var wire 1 % RegWrite $end
$var wire 64 . WriteData [63:0] $end
$var wire 5 / WriteRegister [4:0] $end
$var wire 1 ( clk $end
$upscope $end
$upscope $end
$enddefinitions $end
#0
$dumpvars
b11111 /
b10100000 .
b0 -
b0 ,
bx +
bx *
bx )
0(
b11111 '
b10100000 &
0%
b0 $
b0 #
bx "
bx !
$end
#250000
1%
1(
#500000
0(
#750000
b0 &
b0 .
b0 '
b0 /
b0 "
b0 *
b11111 #
b11111 ,
0%
b0 )
1(
#1000000
0(
#1250000
1%
1(
#1500000
0(
#1750000
b10000001000000100000010000000000000000001 &
b10000001000000100000010000000000000000001 .
b1 '
b1 /
b1 $
b1 -
b0 #
b0 ,
0%
bx !
bx +
b1 )
1(
#2000000
0(
#2250000
1%
1(
#2500000
0(
#2750000
b100000010000001000000100000000000000000010 &
b100000010000001000000100000000000000000010 .
b10 '
b10 /
b10 $
b10 -
b10000001000000100000010000000000000000001 "
b10000001000000100000010000000000000000001 *
b1 #
b1 ,
0%
bx !
bx +
b10 )
1(
#3000000
0(
#3250000
1%
1(
#3500000
0(
#3750000
b110000011000001100000110000000000000000011 &
b110000011000001100000110000000000000000011 .
b11 '
b11 /
b11 $
b11 -
b100000010000001000000100000000000000000010 "
b100000010000001000000100000000000000000010 *
b10 #
b10 ,
0%
bx !
bx +
b11 )
1(
#4000000
0(
#4250000
1%
1(
#4500000
0(
#4750000
b1000000100000010000001000000000000000000100 &
b1000000100000010000001000000000000000000100 .
b100 '
b100 /
b100 $
b100 -
b110000011000001100000110000000000000000011 "
b110000011000001100000110000000000000000011 *
b11 #
b11 ,
0%
bx !
bx +
b100 )
1(
#5000000
0(
#5250000
1%
1(
#5500000
0(
#5750000
b1010000101000010100001010000000000000000101 &
b1010000101000010100001010000000000000000101 .
b101 '
b101 /
b101 $
b101 -
b1000000100000010000001000000000000000000100 "
b1000000100000010000001000000000000000000100 *
b100 #
b100 ,
0%
bx !
bx +
b101 )
1(
#6000000
0(
#6250000
1%
1(
#6500000
0(
#6750000
b1100000110000011000001100000000000000000110 &
b1100000110000011000001100000000000000000110 .
b110 '
b110 /
b110 $
b110 -
b1010000101000010100001010000000000000000101 "
b1010000101000010100001010000000000000000101 *
b101 #
b101 ,
0%
bx !
bx +
b110 )
1(
#7000000
0(
#7250000
1%
1(
#7500000
0(
#7750000
b1110000111000011100001110000000000000000111 &
b1110000111000011100001110000000000000000111 .
b111 '
b111 /
b111 $
b111 -
b1100000110000011000001100000000000000000110 "
b1100000110000011000001100000000000000000110 *
b110 #
b110 ,
0%
bx !
bx +
b111 )
1(
#8000000
0(
#8250000
1%
1(
#8500000
0(
#8750000
b10000001000000100000010000000000000000001000 &
b10000001000000100000010000000000000000001000 .
b1000 '
b1000 /
b1000 $
b1000 -
b1110000111000011100001110000000000000000111 "
b1110000111000011100001110000000000000000111 *
b111 #
b111 ,
0%
bx !
bx +
b1000 )
1(
#9000000
0(
#9250000
1%
1(
#9500000
0(
#9750000
b10010001001000100100010010000000000000001001 &
b10010001001000100100010010000000000000001001 .
b1001 '
b1001 /
b1001 $
b1001 -
b10000001000000100000010000000000000000001000 "
b10000001000000100000010000000000000000001000 *
b1000 #
b1000 ,
0%
bx !
bx +
b1001 )
1(
#10000000
0(
#10250000
1%
1(
#10500000
0(
#10750000
b10100001010000101000010100000000000000001010 &
b10100001010000101000010100000000000000001010 .
b1010 '
b1010 /
b1010 $
b1010 -
b10010001001000100100010010000000000000001001 "
b10010001001000100100010010000000000000001001 *
b1001 #
b1001 ,
0%
bx !
bx +
b1010 )
1(
#11000000
0(
#11250000
1%
1(
#11500000
0(
#11750000
b10110001011000101100010110000000000000001011 &
b10110001011000101100010110000000000000001011 .
b1011 '
b1011 /
b1011 $
b1011 -
b10100001010000101000010100000000000000001010 "
b10100001010000101000010100000000000000001010 *
b1010 #
b1010 ,
0%
bx !
bx +
b1011 )
1(
#12000000
0(
#12250000
1%
1(
#12500000
0(
#12750000
b11000001100000110000011000000000000000001100 &
b11000001100000110000011000000000000000001100 .
b1100 '
b1100 /
b1100 $
b1100 -
b10110001011000101100010110000000000000001011 "
b10110001011000101100010110000000000000001011 *
b1011 #
b1011 ,
0%
bx !
bx +
b1100 )
1(
#13000000
0(
#13250000
1%
1(
#13500000
0(
#13750000
b11010001101000110100011010000000000000001101 &
b11010001101000110100011010000000000000001101 .
b1101 '
b1101 /
b1101 $
b1101 -
b11000001100000110000011000000000000000001100 "
b11000001100000110000011000000000000000001100 *
b1100 #
b1100 ,
0%
bx !
bx +
b1101 )
1(
#14000000
0(
#14250000
1%
1(
#14500000
0(
#14750000
b11100001110000111000011100000000000000001110 &
b11100001110000111000011100000000000000001110 .
b1110 '
b1110 /
b1110 $
b1110 -
b11010001101000110100011010000000000000001101 "
b11010001101000110100011010000000000000001101 *
b1101 #
b1101 ,
0%
bx !
bx +
b1110 )
1(
#15000000
0(
#15250000
1%
1(
#15500000
0(
#15750000
b11110001111000111100011110000000000000001111 &
b11110001111000111100011110000000000000001111 .
b1111 '
b1111 /
b1111 $
b1111 -
b11100001110000111000011100000000000000001110 "
b11100001110000111000011100000000000000001110 *
b1110 #
b1110 ,
0%
bx !
bx +
b1111 )
1(
#16000000
0(
#16250000
1%
1(
#16500000
0(
#16750000
b100000010000001000000100000000000000000010000 &
b100000010000001000000100000000000000000010000 .
b10000 '
b10000 /
b10000 $
b10000 -
b11110001111000111100011110000000000000001111 "
b11110001111000111100011110000000000000001111 *
b1111 #
b1111 ,
0%
bx !
bx +
b10000 )
1(
#17000000
0(
#17250000
1%
1(
#17500000
0(
#17750000
b100010010001001000100100010000000000000010001 &
b100010010001001000100100010000000000000010001 .
b10001 '
b10001 /
b10001 $
b10001 -
b100000010000001000000100000000000000000010000 "
b100000010000001000000100000000000000000010000 *
b10000 #
b10000 ,
0%
bx !
bx +
b10001 )
1(
#18000000
0(
#18250000
1%
1(
#18500000
0(
#18750000
b100100010010001001000100100000000000000010010 &
b100100010010001001000100100000000000000010010 .
b10010 '
b10010 /
b10010 $
b10010 -
b100010010001001000100100010000000000000010001 "
b100010010001001000100100010000000000000010001 *
b10001 #
b10001 ,
0%
bx !
bx +
b10010 )
1(
#19000000
0(
#19250000
1%
1(
#19500000
0(
#19750000
b100110010011001001100100110000000000000010011 &
b100110010011001001100100110000000000000010011 .
b10011 '
b10011 /
b10011 $
b10011 -
b100100010010001001000100100000000000000010010 "
b100100010010001001000100100000000000000010010 *
b10010 #
b10010 ,
0%
bx !
bx +
b10011 )
1(
#20000000
0(
#20250000
1%
1(
#20500000
0(
#20750000
b101000010100001010000101000000000000000010100 &
b101000010100001010000101000000000000000010100 .
b10100 '
b10100 /
b10100 $
b10100 -
b100110010011001001100100110000000000000010011 "
b100110010011001001100100110000000000000010011 *
b10011 #
b10011 ,
0%
bx !
bx +
b10100 )
1(
#21000000
0(
#21250000
1%
1(
#21500000
0(
#21750000
b101010010101001010100101010000000000000010101 &
b101010010101001010100101010000000000000010101 .
b10101 '
b10101 /
b10101 $
b10101 -
b101000010100001010000101000000000000000010100 "
b101000010100001010000101000000000000000010100 *
b10100 #
b10100 ,
0%
bx !
bx +
b10101 )
1(
#22000000
0(
#22250000
1%
1(
#22500000
0(
#22750000
b101100010110001011000101100000000000000010110 &
b101100010110001011000101100000000000000010110 .
b10110 '
b10110 /
b10110 $
b10110 -
b101010010101001010100101010000000000000010101 "
b101010010101001010100101010000000000000010101 *
b10101 #
b10101 ,
0%
bx !
bx +
b10110 )
1(
#23000000
0(
#23250000
1%
1(
#23500000
0(
#23750000
b101110010111001011100101110000000000000010111 &
b101110010111001011100101110000000000000010111 .
b10111 '
b10111 /
b10111 $
b10111 -
b101100010110001011000101100000000000000010110 "
b101100010110001011000101100000000000000010110 *
b10110 #
b10110 ,
0%
bx !
bx +
b10111 )
1(
#24000000
0(
#24250000
1%
1(
#24500000
0(
#24750000
b110000011000001100000110000000000000000011000 &
b110000011000001100000110000000000000000011000 .
b11000 '
b11000 /
b11000 $
b11000 -
b101110010111001011100101110000000000000010111 "
b101110010111001011100101110000000000000010111 *
b10111 #
b10111 ,
0%
bx !
bx +
b11000 )
1(
#25000000
0(
#25250000
1%
1(
#25500000
0(
#25750000
b110010011001001100100110010000000000000011001 &
b110010011001001100100110010000000000000011001 .
b11001 '
b11001 /
b11001 $
b11001 -
b110000011000001100000110000000000000000011000 "
b110000011000001100000110000000000000000011000 *
b11000 #
b11000 ,
0%
bx !
bx +
b11001 )
1(
#26000000
0(
#26250000
1%
1(
#26500000
0(
#26750000
b110100011010001101000110100000000000000011010 &
b110100011010001101000110100000000000000011010 .
b11010 '
b11010 /
b11010 $
b11010 -
b110010011001001100100110010000000000000011001 "
b110010011001001100100110010000000000000011001 *
b11001 #
b11001 ,
0%
bx !
bx +
b11010 )
1(
#27000000
0(
#27250000
1%
1(
#27500000
0(
#27750000
b110110011011001101100110110000000000000011011 &
b110110011011001101100110110000000000000011011 .
b11011 '
b11011 /
b11011 $
b11011 -
b110100011010001101000110100000000000000011010 "
b110100011010001101000110100000000000000011010 *
b11010 #
b11010 ,
0%
bx !
bx +
b11011 )
1(
#28000000
0(
#28250000
1%
1(
#28500000
0(
#28750000
b111000011100001110000111000000000000000011100 &
b111000011100001110000111000000000000000011100 .
b11100 '
b11100 /
b11100 $
b11100 -
b110110011011001101100110110000000000000011011 "
b110110011011001101100110110000000000000011011 *
b11011 #
b11011 ,
0%
bx !
bx +
b11100 )
1(
#29000000
0(
#29250000
1%
1(
#29500000
0(
#29750000
b111010011101001110100111010000000000000011101 &
b111010011101001110100111010000000000000011101 .
b11101 '
b11101 /
b11101 $
b11101 -
b111000011100001110000111000000000000000011100 "
b111000011100001110000111000000000000000011100 *
b11100 #
b11100 ,
0%
bx !
bx +
b11101 )
1(
#30000000
0(
#30250000
1%
1(
#30500000
0(
#30750000
b111100011110001111000111100000000000000011110 &
b111100011110001111000111100000000000000011110 .
b11110 '
b11110 /
b11110 $
b11110 -
b111010011101001110100111010000000000000011101 "
b111010011101001110100111010000000000000011101 *
b11101 #
b11101 ,
0%
bx !
bx +
b11110 )
1(
#31000000
0(
#31250000
1%
1(
#31500000
0(
#31750000
b0 &
b0 .
b0 '
b0 /
b0 $
b0 -
b0 "
b0 *
b11111 #
b11111 ,
0%
b0 !
b0 +
b0 )
1(
#32000000
0(
#32250000
b100000001 &
b100000001 .
b1 '
b1 /
b10000001000000100000010000000000000000001 !
b10000001000000100000010000000000000000001 +
b1 $
b1 -
b0 #
b0 ,
b1 )
1(
#32500000
0(
#32750000
b1000000010 &
b1000000010 .
b10 '
b10 /
b100000010000001000000100000000000000000010 !
b100000010000001000000100000000000000000010 +
b10 $
b10 -
b10000001000000100000010000000000000000001 "
b10000001000000100000010000000000000000001 *
b1 #
b1 ,
b10 )
1(
#33000000
0(
#33250000
b1100000011 &
b1100000011 .
b11 '
b11 /
b110000011000001100000110000000000000000011 !
b110000011000001100000110000000000000000011 +
b11 $
b11 -
b100000010000001000000100000000000000000010 "
b100000010000001000000100000000000000000010 *
b10 #
b10 ,
b11 )
1(
#33500000
0(
#33750000
b10000000100 &
b10000000100 .
b100 '
b100 /
b1000000100000010000001000000000000000000100 !
b1000000100000010000001000000000000000000100 +
b100 $
b100 -
b110000011000001100000110000000000000000011 "
b110000011000001100000110000000000000000011 *
b11 #
b11 ,
b100 )
1(
#34000000
0(
#34250000
b10100000101 &
b10100000101 .
b101 '
b101 /
b1010000101000010100001010000000000000000101 !
b1010000101000010100001010000000000000000101 +
b101 $
b101 -
b1000000100000010000001000000000000000000100 "
b1000000100000010000001000000000000000000100 *
b100 #
b100 ,
b101 )
1(
#34500000
0(
#34750000
b11000000110 &
b11000000110 .
b110 '
b110 /
b1100000110000011000001100000000000000000110 !
b1100000110000011000001100000000000000000110 +
b110 $
b110 -
b1010000101000010100001010000000000000000101 "
b1010000101000010100001010000000000000000101 *
b101 #
b101 ,
b110 )
1(
#35000000
0(
#35250000
b11100000111 &
b11100000111 .
b111 '
b111 /
b1110000111000011100001110000000000000000111 !
b1110000111000011100001110000000000000000111 +
b111 $
b111 -
b1100000110000011000001100000000000000000110 "
b1100000110000011000001100000000000000000110 *
b110 #
b110 ,
b111 )
1(
#35500000
0(
#35750000
b100000001000 &
b100000001000 .
b1000 '
b1000 /
b10000001000000100000010000000000000000001000 !
b10000001000000100000010000000000000000001000 +
b1000 $
b1000 -
b1110000111000011100001110000000000000000111 "
b1110000111000011100001110000000000000000111 *
b111 #
b111 ,
b1000 )
1(
#36000000
0(
#36250000
b100100001001 &
b100100001001 .
b1001 '
b1001 /
b10010001001000100100010010000000000000001001 !
b10010001001000100100010010000000000000001001 +
b1001 $
b1001 -
b10000001000000100000010000000000000000001000 "
b10000001000000100000010000000000000000001000 *
b1000 #
b1000 ,
b1001 )
1(
#36500000
0(
#36750000
b101000001010 &
b101000001010 .
b1010 '
b1010 /
b10100001010000101000010100000000000000001010 !
b10100001010000101000010100000000000000001010 +
b1010 $
b1010 -
b10010001001000100100010010000000000000001001 "
b10010001001000100100010010000000000000001001 *
b1001 #
b1001 ,
b1010 )
1(
#37000000
0(
#37250000
b101100001011 &
b101100001011 .
b1011 '
b1011 /
b10110001011000101100010110000000000000001011 !
b10110001011000101100010110000000000000001011 +
b1011 $
b1011 -
b10100001010000101000010100000000000000001010 "
b10100001010000101000010100000000000000001010 *
b1010 #
b1010 ,
b1011 )
1(
#37500000
0(
#37750000
b110000001100 &
b110000001100 .
b1100 '
b1100 /
b11000001100000110000011000000000000000001100 !
b11000001100000110000011000000000000000001100 +
b1100 $
b1100 -
b10110001011000101100010110000000000000001011 "
b10110001011000101100010110000000000000001011 *
b1011 #
b1011 ,
b1100 )
1(
#38000000
0(
#38250000
b110100001101 &
b110100001101 .
b1101 '
b1101 /
b11010001101000110100011010000000000000001101 !
b11010001101000110100011010000000000000001101 +
b1101 $
b1101 -
b11000001100000110000011000000000000000001100 "
b11000001100000110000011000000000000000001100 *
b1100 #
b1100 ,
b1101 )
1(
#38500000
0(
#38750000
b111000001110 &
b111000001110 .
b1110 '
b1110 /
b11100001110000111000011100000000000000001110 !
b11100001110000111000011100000000000000001110 +
b1110 $
b1110 -
b11010001101000110100011010000000000000001101 "
b11010001101000110100011010000000000000001101 *
b1101 #
b1101 ,
b1110 )
1(
#39000000
0(
#39250000
b111100001111 &
b111100001111 .
b1111 '
b1111 /
b11110001111000111100011110000000000000001111 !
b11110001111000111100011110000000000000001111 +
b1111 $
b1111 -
b11100001110000111000011100000000000000001110 "
b11100001110000111000011100000000000000001110 *
b1110 #
b1110 ,
b1111 )
1(
#39500000
0(
#39750000
b1000000010000 &
b1000000010000 .
b10000 '
b10000 /
b100000010000001000000100000000000000000010000 !
b100000010000001000000100000000000000000010000 +
b10000 $
b10000 -
b11110001111000111100011110000000000000001111 "
b11110001111000111100011110000000000000001111 *
b1111 #
b1111 ,
b10000 )
1(
#40000000
0(
#40250000
b1000100010001 &
b1000100010001 .
b10001 '
b10001 /
b100010010001001000100100010000000000000010001 !
b100010010001001000100100010000000000000010001 +
b10001 $
b10001 -
b100000010000001000000100000000000000000010000 "
b100000010000001000000100000000000000000010000 *
b10000 #
b10000 ,
b10001 )
1(
#40500000
0(
#40750000
b1001000010010 &
b1001000010010 .
b10010 '
b10010 /
b100100010010001001000100100000000000000010010 !
b100100010010001001000100100000000000000010010 +
b10010 $
b10010 -
b100010010001001000100100010000000000000010001 "
b100010010001001000100100010000000000000010001 *
b10001 #
b10001 ,
b10010 )
1(
#41000000
0(
#41250000
b1001100010011 &
b1001100010011 .
b10011 '
b10011 /
b100110010011001001100100110000000000000010011 !
b100110010011001001100100110000000000000010011 +
b10011 $
b10011 -
b100100010010001001000100100000000000000010010 "
b100100010010001001000100100000000000000010010 *
b10010 #
b10010 ,
b10011 )
1(
#41500000
0(
#41750000
b1010000010100 &
b1010000010100 .
b10100 '
b10100 /
b101000010100001010000101000000000000000010100 !
b101000010100001010000101000000000000000010100 +
b10100 $
b10100 -
b100110010011001001100100110000000000000010011 "
b100110010011001001100100110000000000000010011 *
b10011 #
b10011 ,
b10100 )
1(
#42000000
0(
#42250000
b1010100010101 &
b1010100010101 .
b10101 '
b10101 /
b101010010101001010100101010000000000000010101 !
b101010010101001010100101010000000000000010101 +
b10101 $
b10101 -
b101000010100001010000101000000000000000010100 "
b101000010100001010000101000000000000000010100 *
b10100 #
b10100 ,
b10101 )
1(
#42500000
0(
#42750000
b1011000010110 &
b1011000010110 .
b10110 '
b10110 /
b101100010110001011000101100000000000000010110 !
b101100010110001011000101100000000000000010110 +
b10110 $
b10110 -
b101010010101001010100101010000000000000010101 "
b101010010101001010100101010000000000000010101 *
b10101 #
b10101 ,
b10110 )
1(
#43000000
0(
#43250000
b1011100010111 &
b1011100010111 .
b10111 '
b10111 /
b101110010111001011100101110000000000000010111 !
b101110010111001011100101110000000000000010111 +
b10111 $
b10111 -
b101100010110001011000101100000000000000010110 "
b101100010110001011000101100000000000000010110 *
b10110 #
b10110 ,
b10111 )
1(
#43500000
0(
#43750000
b1100000011000 &
b1100000011000 .
b11000 '
b11000 /
b110000011000001100000110000000000000000011000 !
b110000011000001100000110000000000000000011000 +
b11000 $
b11000 -
b101110010111001011100101110000000000000010111 "
b101110010111001011100101110000000000000010111 *
b10111 #
b10111 ,
b11000 )
1(
#44000000
0(
#44250000
b1100100011001 &
b1100100011001 .
b11001 '
b11001 /
b110010011001001100100110010000000000000011001 !
b110010011001001100100110010000000000000011001 +
b11001 $
b11001 -
b110000011000001100000110000000000000000011000 "
b110000011000001100000110000000000000000011000 *
b11000 #
b11000 ,
b11001 )
1(
#44500000
0(
#44750000
b1101000011010 &
b1101000011010 .
b11010 '
b11010 /
b110100011010001101000110100000000000000011010 !
b110100011010001101000110100000000000000011010 +
b11010 $
b11010 -
b110010011001001100100110010000000000000011001 "
b110010011001001100100110010000000000000011001 *
b11001 #
b11001 ,
b11010 )
1(
#45000000
0(
#45250000
b1101100011011 &
b1101100011011 .
b11011 '
b11011 /
b110110011011001101100110110000000000000011011 !
b110110011011001101100110110000000000000011011 +
b11011 $
b11011 -
b110100011010001101000110100000000000000011010 "
b110100011010001101000110100000000000000011010 *
b11010 #
b11010 ,
b11011 )
1(
#45500000
0(
#45750000
b1110000011100 &
b1110000011100 .
b11100 '
b11100 /
b111000011100001110000111000000000000000011100 !
b111000011100001110000111000000000000000011100 +
b11100 $
b11100 -
b110110011011001101100110110000000000000011011 "
b110110011011001101100110110000000000000011011 *
b11011 #
b11011 ,
b11100 )
1(
#46000000
0(
#46250000
b1110100011101 &
b1110100011101 .
b11101 '
b11101 /
b111010011101001110100111010000000000000011101 !
b111010011101001110100111010000000000000011101 +
b11101 $
b11101 -
b111000011100001110000111000000000000000011100 "
b111000011100001110000111000000000000000011100 *
b11100 #
b11100 ,
b11101 )
1(
#46500000
0(
#46750000
b1111000011110 &
b1111000011110 .
b11110 '
b11110 /
b111100011110001111000111100000000000000011110 !
b111100011110001111000111100000000000000011110 +
b11110 $
b11110 -
b111010011101001110100111010000000000000011101 "
b111010011101001110100111010000000000000011101 *
b11101 #
b11101 ,
b11110 )
1(
#47000000
0(
#47250000
b1111100011111 &
b1111100011111 .
b11111 '
b11111 /
b0 !
b0 +
b11111 $
b11111 -
b111100011110001111000111100000000000000011110 "
b111100011110001111000111100000000000000011110 *
b11110 #
b11110 ,
b11111 )
1(
